__init__.py
destroy.py
Destroyer-0.0.1.dist-info/LICENSE
Destroyer-0.0.1.dist-info/METADATA
Destroyer-0.0.1.dist-info/WHEEL
Destroyer-0.0.1.dist-info/top_level.txt
Destroyer-0.0.1.dist-info/RECORD
