Metadata-Version: 2.1
Name: Destroyer
Version: 0.0.1
Summary: A Packagae that destroy the project
Author-email: Noob Master <noobmaster9089@google.com>
License: GNU GENERAL PUBLIC LICENSE
Classifier: Programming Language :: Python :: 3
Classifier: License :: OSI Approved :: MIT License
Classifier: Operating System :: OS Independent
Requires-Python: >=3.7
License-File: LICENSE
